dummy_decorator/__init__.py
dummy_decorator/dummy_decorator.py
dummy_decorator/version.py
dummy_decorator-1.0.0.post1.dist-info/METADATA
dummy_decorator-1.0.0.post1.dist-info/WHEEL
dummy_decorator-1.0.0.post1.dist-info/licenses/LICENSE
dummy_decorator-1.0.0.post1.dist-info/RECORD
